rs_lib/__init__.py
rs_lib/__main__.py
rs_lib/config.py
rs_lib/database.py
rs_lib/gru.py
rs_lib/gru_util.py
rs_lib/rs_lib.py
rs_lib/constants/__init__.py
rs_lib/constants/config.py
rs_lib-0.0.15.dist-info/LICENSE
rs_lib-0.0.15.dist-info/METADATA
rs_lib-0.0.15.dist-info/WHEEL
rs_lib-0.0.15.dist-info/top_level.txt
rs_lib-0.0.15.dist-info/RECORD
