Metadata-Version: 2.1
Name: rs-lib
Version: 0.0.15
Summary: Library for general Remote Sensing code
Home-page: https://github.com/Kortforsyningen/RS_Lib
License: MIT
Project-URL: Changelog, https://github.com/Kortforsyningen/RS_Lib/commits/master
Project-URL: Issue Tracker, https://github.com/Kortforsyningen/RS_Lib/issues
Platform: UNKNOWN
Classifier: Development Status :: 4 - Beta
Classifier: Intended Audience :: Developers
Classifier: License :: OSI Approved :: MIT License
Classifier: Operating System :: Unix
Classifier: Operating System :: Microsoft :: Windows
Classifier: Programming Language :: Python
Classifier: Programming Language :: Python :: 3
Classifier: Programming Language :: Python :: Implementation :: CPython
Classifier: Topic :: Utilities
Requires-Python: >=3.4, !=2.*
Requires-Dist: psycopg2 (>=2.8.5)
Provides-Extra: dev
Requires-Dist: numpy (>=1.19.4) ; extra == 'dev'
Requires-Dist: pytest (>=6.1.2) ; extra == 'dev'
